astronomical/__init__.py
physics/__init__.py
physics/bodies.py
ui/__init__.py
ui/mainwindowapp.py
ammp-0.0.2.dist-info/LICENSE
ammp-0.0.2.dist-info/METADATA
ammp-0.0.2.dist-info/WHEEL
ammp-0.0.2.dist-info/top_level.txt
ammp-0.0.2.dist-info/RECORD
